django_bridge/__init__.py
django_bridge/apps.py
django_bridge/metadata.py
django_bridge/middleware.py
django_bridge/response.py
django_bridge/test.py
django_bridge/views.py
django_bridge/adapters/__init__.py
django_bridge/adapters/forms.py
django_bridge/adapters/registry.py
django_bridge/templates/django_bridge/bootstrap.html
testapp/__init__.py
testapp/apps.py
testapp/settings.py
testapp/urls.py
testapp/tests/__init__.py
django_bridge-0.4.dist-info/METADATA
django_bridge-0.4.dist-info/WHEEL
django_bridge-0.4.dist-info/top_level.txt
django_bridge-0.4.dist-info/RECORD
