Metadata-Version: 2.2
Name: django-bridge
Version: 0.4
Summary: The simple way to build Django applications with modern React frontends
Home-page: https://django-bridge.org
Author: Karl Hobley
Author-email: karl@kaed.uk
License: BSD-3-Clause
Project-URL: Documentation, https://django-bridge.org/docs/
Project-URL: Source, https://github.com/django-bridge/django-bridge/
Project-URL: Tracker, https://github.com/django-bridge/django-bridge/issues
Classifier: Development Status :: 3 - Alpha
Classifier: Intended Audience :: Developers
Classifier: License :: OSI Approved :: BSD License
Classifier: Operating System :: OS Independent
Classifier: Programming Language :: Python
Classifier: Programming Language :: Python :: 3
Classifier: Programming Language :: Python :: 3.11
Classifier: Programming Language :: Python :: 3.12
Classifier: Framework :: Django
Classifier: Framework :: Django :: 4.0
Classifier: Framework :: Django :: 5.0
Requires-Dist: Django<6.0,>=4.0
Requires-Dist: telepath<0.4,>=0.3
Dynamic: author
Dynamic: author-email
Dynamic: classifier
Dynamic: description
Dynamic: description-content-type
Dynamic: home-page
Dynamic: license
Dynamic: project-url
Dynamic: requires-dist
Dynamic: summary
